{
  "dayNum": 11,
  "tests": [
    {
      "name": "example",
      "testFile": "Inputs/Day11/example.txt",
      "result": [
        {
          "correct": "55312",
          "incorrect": []
        },
        {
          "correct": "65601038650482",
          "incorrect": []
        }
      ]
    },
    {
      "name": "input",
      "testFile": "Inputs/Day11/input.txt",
      "result": [
        {
          "correct": "222461",
          "incorrect": []
        },
        {
          "correct": "264350935776416",
          "incorrect": []
        }
      ]
    }
  ]
}
